Workbook

Sheet Assumptions
A1: Unit-economics assumptions (ILLUSTRATIVE — replace with real data)
A2: Overwrite column B; the Model sheet recomputes. THB unless noted.
A3: Input | B3: Value | C3: Source / note
A4: FX rate (THB per USD) | B4: 35 | C4: set to current
A5: Anthropic blended token cost (USD / 1M tokens) | B5: 4 | C5: Sonnet-reasoning + Haiku-relay mix w/ prompt caching; ai-models.ts tiering
A6: Token cost (THB / 1k tokens) | B6: =B5/1000*B4 | C6: derived = USD/1M ÷ 1000 × FX
A7: Infra base (THB / mo, platform) | B7: 52500 | C7: ≈ $1,500/mo Alibaba Cloud Bangkok, lean
A8: Paying tenants | B8: 50 | C8: replace with live count
A9: Infra allocation (THB / tenant / mo) | B9: =B7/B8 | C9: derived = infra base ÷ tenants (falls as tenants grow)
A10: Starter price (THB / mo) | B10: 990 | C10: billing PLAN_SEED
A11: Pro price (THB / mo) | B11: 2900 | C11: billing PLAN_SEED
A12: Enterprise ARPU (THB / mo) | B12: 15000 | C12: custom-priced; illustrative
A13: Pro avg AI usage (tokens / day) | B13: 60000 | C13: 30% of 200k included; replace w/ ai_token_usage actuals
A14: Enterprise avg AI usage (tokens / day) | B14: 600000 | C14: 30% of 2M included; replace w/ ai_token_usage actuals
A15: Plan mix — Starter | B15: 0.2 | C15: share of paying tenants
A16: Plan mix — Pro | B16: 0.7 | C16: share of paying tenants
A17: Plan mix — Enterprise | B17: 0.1 | C17: share of paying tenants
A18: Blended CAC (THB) | B18: 4500 | C18: self-serve + light sales; illustrative
A19: Monthly logo churn | B19: 0.03 | C19: illustrative SMB; saas-metrics churn.churn_rate_30d_pct
A20: Target gross margin | B20: 0.75 | C20: guardrail

Sheet Model
A1: Unit economics — computed (live formulas)
A3: Per-plan economics
A4: Plan | B4: Price/mo | C4: AI COGS/mo | D4: Infra alloc | E4: Total COGS | F4: Gross profit | G4: Gross margin
A5: Starter | B5: =Assumptions!$B$10 | C5: 0 | D5: =Assumptions!$B$9 | E5: =C5+D5 | F5: =B5-E5 | G5: =IF(B5=0,0,F5/B5)
A6: Pro | B6: =Assumptions!$B$11 | C6: =Assumptions!$B$13*30/1000*Assumptions!$B$6 | D6: =Assumptions!$B$9 | E6: =C6+D6 | F6: =B6-E6 | G6: =IF(B6=0,0,F6/B6)
A7: Enterprise | B7: =Assumptions!$B$12 | C7: =Assumptions!$B$14*30/1000*Assumptions!$B$6 | D7: =Assumptions!$B$9 | E7: =C7+D7 | F7: =B7-E7 | G7: =IF(B7=0,0,F7/B7)
A10: Blended SaaS metrics
A11: Blended ARPU (THB/mo) | B11: =Assumptions!$B$15*Assumptions!$B$10+Assumptions!$B$16*Assumptions!$B$11+Assumptions!$B$17*Assumptions!$B$12 | C11: Σ(mix×price); saas-metrics revenue.arpu
A12: MRR (THB) | B12: =B11*Assumptions!$B$8 | C12: ARPU × paying tenants; saas-metrics revenue.mrr
A13: ARR (THB) | B13: =B12*12 | C13: MRR × 12; saas-metrics revenue.arr
A14: Blended COGS / tenant (THB/mo) | B14: =Assumptions!$B$15*(Assumptions!$B$9)+Assumptions!$B$16*(C6+Assumptions!$B$9)+Assumptions!$B$17*(C7+Assumptions!$B$9) | C14: mix-weighted infra + AI COGS
A15: Blended gross margin | B15: =(B11-B14)/B11 | C15: (ARPU − blended COGS) / ARPU
A16: CAC payback (months) | B16: =Assumptions!$B$18/(B11*B15) | C16: CAC / (ARPU × GM)
A17: LTV (THB) | B17: =(B11*B15)/Assumptions!$B$19 | C17: (ARPU × GM) / monthly churn
A18: LTV : CAC | B18: =B17/Assumptions!$B$18 | C18: LTV / CAC (≥3 healthy)
A20: Guardrail: no unlimited AI tier (finite ai_tokens_daily_max per plan); overage above the included cap is billed (ai_overage_rate_thb_per_1k); off-Opus tiering keeps blended token COGS ~0.14 THB/1k. Watch Starter — margin-negative on infra allocation until tenant count amortizes the base.
